cysecuretools/__about__.py
cysecuretools/__init__.py
cysecuretools/__main__.py
cysecuretools/api_common.py
cysecuretools/api_mxs40sv2.py
cysecuretools/api_mxs40v1.py
cysecuretools/api_traveo_t2g.py
cysecuretools/cli.py
cysecuretools/cli_creator.py
cysecuretools/cli_mxs40sv2.py
cysecuretools/cli_mxs40v1.py
cysecuretools/cli_traveo_t2g.py
cysecuretools/main.py
cysecuretools/pkg_globals.py
cysecuretools/settings.json
cysecuretools/core/__init__.py
cysecuretools/core/bitops.py
cysecuretools/core/connect_helper.py
cysecuretools/core/crc.py
cysecuretools/core/cy_bootloader_map_parser.py
cysecuretools/core/dependecy_validator.py
cysecuretools/core/deprecated.py
cysecuretools/core/entrance_exam_base.py
cysecuretools/core/enums.py
cysecuretools/core/exceptions.py
cysecuretools/core/json_helper.py
cysecuretools/core/jsonpath.py
cysecuretools/core/key_data.py
cysecuretools/core/key_helper.py
cysecuretools/core/logging_configurator.py
cysecuretools/core/logging_formatter.py
cysecuretools/core/memory_area.py
cysecuretools/core/memory_map_base.py
cysecuretools/core/mtb_tools_discovery.py
cysecuretools/core/ocd_settings.py
cysecuretools/core/policy_filter_base.py
cysecuretools/core/policy_parser_base.py
cysecuretools/core/policy_validator_base.py
cysecuretools/core/progress_bar.py
cysecuretools/core/project_base.py
cysecuretools/core/ram_app_loader_base.py
cysecuretools/core/register_map_base.py
cysecuretools/core/signtool_base.py
cysecuretools/core/strops.py
cysecuretools/core/target_builder.py
cysecuretools/core/target_director.py
cysecuretools/core/version_provider.py
cysecuretools/core/voltage_tool.py
cysecuretools/core/key_handlers/__init__.py
cysecuretools/core/key_handlers/ec_handler.py
cysecuretools/core/key_handlers/pem_key.py
cysecuretools/core/key_handlers/rsa_handler.py
cysecuretools/core/provisioning_flows/__init__.py
cysecuretools/core/provisioning_flows/app_loading_flow.py
cysecuretools/core/provisioning_flows/application.py
cysecuretools-6.1.0.dist-info/LICENSE
cysecuretools-6.1.0.dist-info/METADATA
cysecuretools-6.1.0.dist-info/WHEEL
cysecuretools-6.1.0.dist-info/entry_points.txt
cysecuretools-6.1.0.dist-info/top_level.txt
cysecuretools-6.1.0.dist-info/RECORD
