Metadata-Version: 2.1
Name: cysecuretools
Version: 6.1.0
Summary: Python tools for provisioning Cypress/Infineon MCUs
Home-page: https://github.com/Infineon/cysecuretools
Author: Cypress Semiconductor Corporation (an Infineon company)
License: Apache 2.0
Classifier: License :: OSI Approved :: Apache Software License
Classifier: Programming Language :: Python :: 3.8
Classifier: Programming Language :: Python :: 3.9
Classifier: Programming Language :: Python :: 3.10
Classifier: Programming Language :: Python :: 3.11
Classifier: Programming Language :: Python :: 3.12
Classifier: Operating System :: OS Independent
Classifier: Topic :: Software Development :: Embedded Systems
Requires-Python: >=3.8
License-File: LICENSE
Requires-Dist: setuptools==69.5.1
Requires-Dist: cryptography==36.0.1
Requires-Dist: click==8.0.4
Requires-Dist: intelhex==2.3.0
Requires-Dist: python-jose==3.3.0
Requires-Dist: jsonschema<=4.22.0,>=4.0.0
Requires-Dist: cbor==1.0.0
Requires-Dist: packaging==21.3
Requires-Dist: lief==0.14.1
